naturf/__init__.py
naturf/config.py
naturf/driver.py
naturf/nodes.py
naturf/output.py
naturf/data/C-5.cpg
naturf/data/C-5.dbf
naturf/data/C-5.prj
naturf/data/C-5.sbn
naturf/data/C-5.sbx
naturf/data/C-5.shp
naturf/data/C-5.shx
naturf-1.0.4.dist-info/METADATA
naturf-1.0.4.dist-info/WHEEL
naturf-1.0.4.dist-info/licenses/LICENSE
naturf-1.0.4.dist-info/RECORD
